sql_query_parser/__init__.py
sql_query_parser/condition.py
sql_query_parser/configurations.py
sql_query_parser/configurations_test.py
sql_query_parser/py.typed
sql_query_parser/query.py
sql_query_parser/sql_query_parser.py
sql_query_parser/table.py
sql_query_parser/table_test.py
sql_query_parser/word_recognition.py
sql_query_parser/conditions/__init__.py
sql_query_parser/conditions/conditions_parser.py
sql_query_parser/exceptions/__init__.py
sql_query_parser/exceptions/different_conditions_in_parenthesis_exception.py
sql_query_parser/exceptions/object_blocked_exception.py
sql_query_parser/functions/__init__.py
sql_query_parser/functions/count.py
sql_query_parser/functions/function_parser.py
sql_query_parser/general_purpose/__init__.py
sql_query_parser/general_purpose/from_table.py
sql_query_parser/general_purpose/general_purpose_parser.py
sql_query_parser/general_purpose/select_column.py
sql_query_parser/general_purpose/where_condition.py
sql_query_parser/keywords/__init__.py
sql_query_parser/keywords/from_.py
sql_query_parser/keywords/keyword_parser.py
sql_query_parser/keywords/select.py
sql_query_parser/keywords/select_test.py
sql_query_parser/keywords/where.py
sql_query_parser-0.0.2.dist-info/LICENSE
sql_query_parser-0.0.2.dist-info/METADATA
sql_query_parser-0.0.2.dist-info/WHEEL
sql_query_parser-0.0.2.dist-info/top_level.txt
sql_query_parser-0.0.2.dist-info/RECORD
