Metadata-Version: 2.1
Name: sql-query-parser
Version: 0.0.2
Summary: An advanced python sql query parser. IS AN ALPHA VERSION
Home-page: https://github.com/Morry98/sql-parser
Download-URL: 
Author: ('Matteo Morando',)
License: MIT License        
Project-URL: Bug Tracker, https://github.com/Morry98/sql-parser/issues
Project-URL: Source Code, https://github.com/Morry98/sql-parser
Keywords: sql,parser,sql-parser,sql-query-parser
Platform: Windows
Platform: Linux
Platform: Solaris
Platform: Mac OS-X
Platform: Unix
Requires-Python: >=3.10
License-File: LICENSE
Requires-Dist: colorama (==0.4.4)
Requires-Dist: loguru (==0.6.0)
Requires-Dist: win32-setctime (==1.1.0)
